content_types/__init__.py
content_types/py.typed
content_types-0.3.0.dist-info/METADATA
content_types-0.3.0.dist-info/WHEEL
content_types-0.3.0.dist-info/entry_points.txt
content_types-0.3.0.dist-info/licenses/LICENSE
content_types-0.3.0.dist-info/RECORD
