Metadata-Version: 2.4
Name: content-types
Version: 0.3.0
Summary: A library to map file extensions to content types and vice versa.
Project-URL: Homepage, https://github.com/mikeckennedy/content-types
Project-URL: Bug Reports, https://github.com/mikeckennedy/content-types/issues
Project-URL: Source, https://github.com/mikeckennedy/content-types
Author-email: Michael Kennedy <mikeckennedy@gmail.com>
License-Expression: MIT
License-File: LICENSE
Keywords: content-type,file extensions,mapping,mime
Classifier: Intended Audience :: Developers
Classifier: License :: OSI Approved :: MIT License
Classifier: Operating System :: OS Independent
Classifier: Programming Language :: Python :: 3.10
Classifier: Programming Language :: Python :: 3.11
Classifier: Programming Language :: Python :: 3.12
Classifier: Programming Language :: Python :: 3.13
Classifier: Programming Language :: Python :: 3.14
Classifier: Topic :: Internet :: WWW/HTTP
Classifier: Topic :: Software Development :: Libraries :: Python Modules
Requires-Python: >=3.10
